rtl/dmem.v
module dmem(
    input clk,
    input [15:0] addr,
    input [15:0] write_data,
    input mem_write,
    input mem_read,
    output reg [15:0] read_data
);
    // reg [15:0] mem [0:65535];  // 64K words (128KB)
    reg [15:0] mem [0:2];

    always @(posedge clk) begin
        if (mem_write)
            mem[addr[15:1]] <= write_data;  // Word addressing
    end

    always @(*) begin
        if (mem_read)
            read_data = mem[addr[15:1]];  // Asynchronous read
        else
            read_data = 16'b0;
    end
endmodule

rtl/alu.v
module alu(
    input [15:0] a,
    input [15:0] b,
    input [1:0] op,
    output reg [15:0] result,
    output zero
);
    always @(*) begin
        case (op)
            2'b00: result = a + b;   // ADD
            2'b01: result = a - b;   // SUB
            2'b10: result = a & b;   // AND
            2'b11: result = a | b;   // OR
            default: result = 16'b0;
        endcase
    end
    assign zero = (result == 16'b0);
endmodule

rtl/control.v
module control(
    input [3:0] opcode,
    output reg reg_write,
    output reg mem_read,
    output reg mem_write,
    output reg mem_to_reg,
    output reg [1:0] alu_op,
    output reg branch,
    output reg jump,
    output reg alu_src,
    output reg reg_dst
);
    always @(*) begin
        case (opcode)
            // ADD
            4'b0000: begin
                {reg_write, mem_read, mem_write, mem_to_reg} = 4'b1000;
                {alu_op, branch, jump} = 3'b000;
                {alu_src, reg_dst} = 2'b01;
            end
            // SUB
            4'b0001: begin
                {reg_write, mem_read, mem_write, mem_to_reg} = 4'b1000;
                {alu_op, branch, jump} = 3'b010;
                {alu_src, reg_dst} = 2'b01;
            end
            // AND
            4'b0010: begin
                {reg_write, mem_read, mem_write, mem_to_reg} = 4'b1000;
                {alu_op, branch, jump} = 3'b100;
                {alu_src, reg_dst} = 2'b01;
            end
            // OR
            4'b0011: begin
                {reg_write, mem_read, mem_write, mem_to_reg} = 4'b1000;
                {alu_op, branch, jump} = 3'b110;
                {alu_src, reg_dst} = 2'b01;
            end
            // LW
            4'b0100: begin
                {reg_write, mem_read, mem_write, mem_to_reg} = 4'b1101;
                {alu_op, branch, jump} = 3'b000;
                {alu_src, reg_dst} = 2'b10;
            end
            // SW
            4'b0101: begin
                {reg_write, mem_read, mem_write, mem_to_reg} = 4'b0010;
                {alu_op, branch, jump} = 3'b000;
                {alu_src, reg_dst} = 2'b10;
            end
            // BEQ
            4'b0110: begin
                {reg_write, mem_read, mem_write, mem_to_reg} = 4'b0000;
                {alu_op, branch, jump} = 3'b011;
                {alu_src, reg_dst} = 2'b00;
            end
            // JMP
            4'b0111: begin
                {reg_write, mem_read, mem_write, mem_to_reg} = 4'b0000;
                {alu_op, branch, jump} = 3'bx1x;
                {alu_src, reg_dst} = 2'bxx;
            end
            // Default: NOP
            default: begin
                {reg_write, mem_read, mem_write, mem_to_reg} = 4'b0000;
                {alu_op, branch, jump} = 3'b000;
                {alu_src, reg_dst} = 2'b00;
            end
        endcase
    end
endmodule

rtl/regfile.v
module regfile(
    input clk,
    input rst,
    input [3:0] read_reg1,
    input [3:0] read_reg2,
    output reg [15:0] read_data1,
    output reg [15:0] read_data2,
    input write_en,
    input [3:0] write_reg,
    input [15:0] write_data
);
    reg [15:0] registers [15:0];

    // Initialize r0=0, r1=1, others=0
    integer i;
    always @(posedge clk or posedge rst) begin
        if (rst) begin
            for (i = 0; i < 16; i = i + 1) registers[i] <= 16'b0;
            registers[1] <= 16'b1;
        end
        else if (write_en) begin
            // Prevent writes to r0 and r1
            if (write_reg != 4'd0 && write_reg != 4'd1)
                registers[write_reg] <= write_data;
        end
    end

    // Read ports with r0/r1 override
    always @(*) begin
        read_data1 = (read_reg1 == 4'd0) ? 16'b0 : 
                    (read_reg1 == 4'd1) ? 16'b1 : registers[read_reg1];
        read_data2 = (read_reg2 == 4'd0) ? 16'b0 : 
                    (read_reg2 == 4'd1) ? 16'b1 : registers[read_reg2];
    end
endmodule

rtl/imem.v
module imem(
    input [15:0] addr,
    output reg [15:0] instruction
);
    // reg [15:0] mem [0:65535];  // 64K words (128KB)
    reg [15:0] mem [0:10];

    initial begin
        // Load instructions from file at startup
        $readmemh("mem/program.mem", mem);
    end

    always @(*) begin
        instruction = mem[addr[15:1]];  // Word addressing
    end
endmodule

rtl/cpu.v
module cpu(
    input clk,
    input rst
);
    // Program Counter
    reg [15:0] PC;
    wire [15:0] PC_plus_2 = PC + 2;

    // Instruction fetch
    wire [15:0] instruction;
    imem imem_inst(.addr(PC), .instruction(instruction));

    // Instruction decode
    wire [3:0] opcode = instruction[15:12];
    wire [3:0] Rs = instruction[11:8];
    wire [3:0] Rt = instruction[7:4];
    wire [3:0] Rd_or_Offset = instruction[3:0];
    wire [11:0] Offset12 = instruction[11:0];

    // Register file
    wire [15:0] read_data1, read_data2;
    wire reg_write;
    wire [3:0] write_reg;
    wire [15:0] write_data;
    regfile regfile_inst(
        .clk(clk),
        .rst(rst),
        .read_reg1(Rs),
        .read_reg2(Rt),
        .read_data1(read_data1),
        .read_data2(read_data2),
        .write_en(reg_write),
        .write_reg(write_reg),
        .write_data(write_data)
    );

    // Control unit
    wire mem_read, mem_write, mem_to_reg, branch, jump;
    wire [1:0] alu_op;
    wire alu_src, reg_dst;
    control control_inst(
        .opcode(opcode),
        .reg_write(reg_write),
        .mem_read(mem_read),
        .mem_write(mem_write),
        .mem_to_reg(mem_to_reg),
        .alu_op(alu_op),
        .branch(branch),
        .jump(jump),
        .alu_src(alu_src),
        .reg_dst(reg_dst)
    );

    // Sign extension
    wire [15:0] sign_ext_offset = {{12{Rd_or_Offset[3]}}, Rd_or_Offset};

    // ALU input selection
    wire [15:0] alu_b = alu_src ? sign_ext_offset : read_data2;

    // ALU
    wire [15:0] alu_result;
    wire zero;
    alu alu_inst(
        .a(read_data1),
        .b(alu_b),
        .op(alu_op),
        .result(alu_result),
        .zero(zero)
    );

    // Data memory
    wire [15:0] mem_read_data;
    dmem dmem_inst(
        .clk(clk),
        .addr(alu_result),
        .write_data(read_data2),
        .mem_write(mem_write),
        .mem_read(mem_read),
        .read_data(mem_read_data)
    );

    // Write-back MUX
    assign write_data = mem_to_reg ? mem_read_data : alu_result;

    // Register destination MUX
    assign write_reg = reg_dst ? Rd_or_Offset : Rt;

    // Branch/jump logic
    wire branch_condition = branch & zero;
    wire [15:0] branch_target = PC_plus_2 + (sign_ext_offset << 1);
    wire [15:0] jump_target = {4'b0, Offset12} << 1;
    wire [15:0] next_PC = 
        jump          ? jump_target :
        branch_condition ? branch_target : 
        PC_plus_2;

    // PC update
    always @(posedge clk or posedge rst) begin
        if (rst) PC <= 16'b0;
        else PC <= next_PC;
    end
endmodule

testbench/tb_cpu.v
module tb_cpu;
    reg clk = 0;
    reg rst = 1;
    
    cpu uut (.*);
    
    always #5 clk = ~clk;  // 10ns clock period

    always @(posedge clk) begin
        $display("PC=%d | r2=%d | r3=%d | r4=%d | r5=%d | r6=%d | z=%d", 
            uut.PC,
            uut.regfile_inst.registers[2],
            uut.regfile_inst.registers[3],
            uut.regfile_inst.registers[4],
            uut.regfile_inst.registers[5],
            uut.regfile_inst.registers[6],
            uut.zero_flag);
        end
            
    initial begin
        $dumpfile("cpu.vcd");
        $dumpvars(0, tb_cpu);
        #5 rst = 0;       // Release reset after 10ns
        #600 $finish;
    end
endmodule

rtl/cpu.vcd
$date
	Tue Jun  3 11:57:37 2025
$end
$version
	Icarus Verilog
$end
$timescale
	1s
$end
$scope module tb_cpu $end
$var reg 1 ! clk $end
$var reg 1 " rst $end
$scope module uut $end
$var wire 1 # branch_condition $end
$var wire 1 ! clk $end
$var wire 1 " rst $end
$var wire 1 $ zero $end
$var wire 4 % write_reg [3:0] $end
$var wire 16 & write_data [15:0] $end
$var wire 16 ' sign_ext_offset [15:0] $end
$var wire 1 ( reg_write $end
$var wire 1 ) reg_dst $end
$var wire 16 * read_data2 [15:0] $end
$var wire 16 + read_data1 [15:0] $end
$var wire 4 , opcode [3:0] $end
$var wire 16 - next_PC [15:0] $end
$var wire 1 . mem_write $end
$var wire 1 / mem_to_reg $end
$var wire 16 0 mem_read_data [15:0] $end
$var wire 1 1 mem_read $end
$var wire 16 2 jump_target [15:0] $end
$var wire 1 3 jump $end
$var wire 16 4 instruction [15:0] $end
$var wire 16 5 branch_target [15:0] $end
$var wire 1 6 branch $end
$var wire 1 7 alu_src $end
$var wire 16 8 alu_result [15:0] $end
$var wire 2 9 alu_op [1:0] $end
$var wire 16 : alu_b [15:0] $end
$var wire 4 ; Rt [3:0] $end
$var wire 4 < Rs [3:0] $end
$var wire 4 = Rd_or_Offset [3:0] $end
$var wire 16 > PC_plus_2 [15:0] $end
$var wire 12 ? Offset12 [11:0] $end
$var reg 16 @ PC [15:0] $end
$scope module alu_inst $end
$var wire 16 A b [15:0] $end
$var wire 1 $ zero $end
$var wire 2 B op [1:0] $end
$var wire 16 C a [15:0] $end
$var reg 16 D result [15:0] $end
$upscope $end
$scope module control_inst $end
$var wire 4 E opcode [3:0] $end
$var reg 2 F alu_op [1:0] $end
$var reg 1 7 alu_src $end
$var reg 1 6 branch $end
$var reg 1 3 jump $end
$var reg 1 1 mem_read $end
$var reg 1 / mem_to_reg $end
$var reg 1 . mem_write $end
$var reg 1 ) reg_dst $end
$var reg 1 ( reg_write $end
$upscope $end
$scope module dmem_inst $end
$var wire 16 G addr [15:0] $end
$var wire 1 ! clk $end
$var wire 1 1 mem_read $end
$var wire 1 . mem_write $end
$var wire 16 H write_data [15:0] $end
$var reg 16 I read_data [15:0] $end
$upscope $end
$scope module imem_inst $end
$var wire 16 J addr [15:0] $end
$var reg 16 K instruction [15:0] $end
$upscope $end
$scope module regfile_inst $end
$var wire 1 ! clk $end
$var wire 4 L read_reg1 [3:0] $end
$var wire 4 M read_reg2 [3:0] $end
$var wire 1 " rst $end
$var wire 16 N write_data [15:0] $end
$var wire 1 ( write_en $end
$var wire 4 O write_reg [3:0] $end
$var reg 16 P read_data1 [15:0] $end
$var reg 16 Q read_data2 [15:0] $end
$var integer 32 R i [31:0] $end
$upscope $end
$upscope $end
$upscope $end
$enddefinitions $end
$comment Show the parameter values. $end
$dumpall
$end
#0
$dumpvars
b10000 R
b0 Q
b0 P
b0 O
b0 N
b0 M
b0 L
b0 K
b0 J
b0 I
b0 H
b0 G
b0 F
b0 E
b0 D
b0 C
b0 B
b0 A
b0 @
b0 ?
b10 >
b0 =
b0 <
b0 ;
b0 :
b0 9
b0 8
07
06
b10 5
b0 4
03
b0 2
01
b0 0
0/
0.
b10 -
b0 ,
b0 +
b0 *
1)
1(
b0 '
b0 &
b0 %
1$
0#
1"
0!
$end
#5
b10000 R
1!
#10
0!
0"
#15
1#
b10001101000 2
b100 %
b100 O
16
b1100 -
b1000110100 ?
b100 '
b100 =
b11 ;
b11 M
b10 <
b10 L
b1 ,
b1 E
b1001000110100 4
b1001000110100 K
b1100 5
b100 >
b10 @
b10 J
1!
#20
0!
#25
bx &
bx N
bx :
bx A
x$
bx 8
bx D
bx G
0#
b0xxxxxxxxxxxx0 2
bx %
bx O
bx *
bx H
bx Q
bx +
bx C
bx P
0)
06
0(
b1110 -
bx ?
bx '
bx =
bx ;
bx M
bx <
bx L
bx ,
bx E
bx 4
bx K
bx 5
b1110 >
b1100 @
b1100 J
1!
#30
0!
#35
b10000 -
b10000 >
b1110 @
b1110 J
1!
#40
0!
#45
b10010 -
b10010 >
b10000 @
b10000 J
1!
#50
0!
#55
b10100 -
b10100 >
b10010 @
b10010 J
1!
#60
0!
#65
b10110 -
b10110 >
b10100 @
b10100 J
1!
#70
0!
#75
b11000 -
b11000 >
b10110 @
b10110 J
1!
#80
0!
#85
b11010 -
b11010 >
b11000 @
b11000 J
1!
#90
0!
#95
b11100 -
b11100 >
b11010 @
b11010 J
1!
#100
0!
#105
b11110 -
b11110 >
b11100 @
b11100 J
1!
#110
0!
#115
b100000 -
b100000 >
b11110 @
b11110 J
1!
#120
0!
#125
b100010 -
b100010 >
b100000 @
b100000 J
1!
#130
0!
#135
b100100 -
b100100 >
b100010 @
b100010 J
1!
#140
0!
#145
b100110 -
b100110 >
b100100 @
b100100 J
1!
#150
0!
#155
b101000 -
b101000 >
b100110 @
b100110 J
1!
#160
0!
#165
b101010 -
b101010 >
b101000 @
b101000 J
1!
#170
0!
#175
b101100 -
b101100 >
b101010 @
b101010 J
1!
#180
0!
#185
b101110 -
b101110 >
b101100 @
b101100 J
1!
#190
0!
#195
b110000 -
b110000 >
b101110 @
b101110 J
1!
#200
0!
#205
b110010 -
b110010 >
b110000 @
b110000 J
1!
#210
0!
#215
b110100 -
b110100 >
b110010 @
b110010 J
1!
#220
0!
#225
b110110 -
b110110 >
b110100 @
b110100 J
1!
#230
0!
#235
b111000 -
b111000 >
b110110 @
b110110 J
1!
#240
0!
#245
b111010 -
b111010 >
b111000 @
b111000 J
1!
#250
0!
#255
b111100 -
b111100 >
b111010 @
b111010 J
1!
#260
0!
#265
b111110 -
b111110 >
b111100 @
b111100 J
1!
#270
0!
#275
b1000000 -
b1000000 >
b111110 @
b111110 J
1!
#280
0!
#285
b1000010 -
b1000010 >
b1000000 @
b1000000 J
1!
#290
0!
#295
b1000100 -
b1000100 >
b1000010 @
b1000010 J
1!
#300
0!
#305
b1000110 -
b1000110 >
b1000100 @
b1000100 J
1!
#310
0!
#315
b1001000 -
b1001000 >
b1000110 @
b1000110 J
1!
#320
0!
#325
b1001010 -
b1001010 >
b1001000 @
b1001000 J
1!
#330
0!
#335
b1001100 -
b1001100 >
b1001010 @
b1001010 J
1!
#340
0!
#345
b1001110 -
b1001110 >
b1001100 @
b1001100 J
1!
#350
0!
#355
b1010000 -
b1010000 >
b1001110 @
b1001110 J
1!
#360
0!
#365
b1010010 -
b1010010 >
b1010000 @
b1010000 J
1!
#370
0!
#375
b1010100 -
b1010100 >
b1010010 @
b1010010 J
1!
#380
0!
#385
b1010110 -
b1010110 >
b1010100 @
b1010100 J
1!
#390
0!
#395
b1011000 -
b1011000 >
b1010110 @
b1010110 J
1!
#400
0!
#405
b1011010 -
b1011010 >
b1011000 @
b1011000 J
1!
#410
0!
#415
b1011100 -
b1011100 >
b1011010 @
b1011010 J
1!
#420
0!
#425
b1011110 -
b1011110 >
b1011100 @
b1011100 J
1!
#430
0!
#435
b1100000 -
b1100000 >
b1011110 @
b1011110 J
1!
#440
0!
#445
b1100010 -
b1100010 >
b1100000 @
b1100000 J
1!
#450
0!
#455
b1100100 -
b1100100 >
b1100010 @
b1100010 J
1!
#460
0!
#465
b1100110 -
b1100110 >
b1100100 @
b1100100 J
1!
#470
0!
#475
b1101000 -
b1101000 >
b1100110 @
b1100110 J
1!
#480
0!
#485
b1101010 -
b1101010 >
b1101000 @
b1101000 J
1!
#490
0!
#495
b1101100 -
b1101100 >
b1101010 @
b1101010 J
1!
#500
0!
#505
b1101110 -
b1101110 >
b1101100 @
b1101100 J
1!
#510
0!
#515
b1110000 -
b1110000 >
b1101110 @
b1101110 J
1!
#520
0!
#525
b1110010 -
b1110010 >
b1110000 @
b1110000 J
1!
#530
0!
#535
b1110100 -
b1110100 >
b1110010 @
b1110010 J
1!
#540
0!
#545
b1110110 -
b1110110 >
b1110100 @
b1110100 J
1!
#550
0!
#555
b1111000 -
b1111000 >
b1110110 @
b1110110 J
1!
#560
0!
#565
b1111010 -
b1111010 >
b1111000 @
b1111000 J
1!
#570
0!
#575
b1111100 -
b1111100 >
b1111010 @
b1111010 J
1!
#580
0!
#585
b1111110 -
b1111110 >
b1111100 @
b1111100 J
1!
#590
0!
#595
b10000000 -
b10000000 >
b1111110 @
b1111110 J
1!
#600
0!
#605
b10000010 -
b10000010 >
b10000000 @
b10000000 J
1!
#610
0!
#615
b10000100 -
b10000100 >
b10000010 @
b10000010 J
1!
#620
0!
#625
b10000110 -
b10000110 >
b10000100 @
b10000100 J
1!
#630
0!
#635
b10001000 -
b10001000 >
b10000110 @
b10000110 J
1!
#640
0!
#645
b10001010 -
b10001010 >
b10001000 @
b10001000 J
1!
#650
0!
#655
b10001100 -
b10001100 >
b10001010 @
b10001010 J
1!
#660
0!
#665
b10001110 -
b10001110 >
b10001100 @
b10001100 J
1!
#670
0!
#675
b10010000 -
b10010000 >
b10001110 @
b10001110 J
1!
#680
0!
#685
b10010010 -
b10010010 >
b10010000 @
b10010000 J
1!
#690
0!
#695
b10010100 -
b10010100 >
b10010010 @
b10010010 J
1!
#700
0!
#705
b10010110 -
b10010110 >
b10010100 @
b10010100 J
1!
#710
0!
#715
b10011000 -
b10011000 >
b10010110 @
b10010110 J
1!
#720
0!
#725
b10011010 -
b10011010 >
b10011000 @
b10011000 J
1!
#730
0!
#735
b10011100 -
b10011100 >
b10011010 @
b10011010 J
1!
#740
0!
#745
b10011110 -
b10011110 >
b10011100 @
b10011100 J
1!
#750
0!
#755
b10100000 -
b10100000 >
b10011110 @
b10011110 J
1!
#760
0!
#765
b10100010 -
b10100010 >
b10100000 @
b10100000 J
1!
#770
0!
#775
b10100100 -
b10100100 >
b10100010 @
b10100010 J
1!
#780
0!
#785
b10100110 -
b10100110 >
b10100100 @
b10100100 J
1!
#790
0!
#795
b10101000 -
b10101000 >
b10100110 @
b10100110 J
1!
#800
0!
#805
b10101010 -
b10101010 >
b10101000 @
b10101000 J
1!
#810
0!
#815
b10101100 -
b10101100 >
b10101010 @
b10101010 J
1!
#820
0!
#825
b10101110 -
b10101110 >
b10101100 @
b10101100 J
1!
#830
0!
#835
b10110000 -
b10110000 >
b10101110 @
b10101110 J
1!
#840
0!
#845
b10110010 -
b10110010 >
b10110000 @
b10110000 J
1!
#850
0!
#855
b10110100 -
b10110100 >
b10110010 @
b10110010 J
1!
#860
0!
#865
b10110110 -
b10110110 >
b10110100 @
b10110100 J
1!
#870
0!
#875
b10111000 -
b10111000 >
b10110110 @
b10110110 J
1!
#880
0!
#885
b10111010 -
b10111010 >
b10111000 @
b10111000 J
1!
#890
0!
#895
b10111100 -
b10111100 >
b10111010 @
b10111010 J
1!
#900
0!
#905
b10111110 -
b10111110 >
b10111100 @
b10111100 J
1!
#910
0!
#915
b11000000 -
b11000000 >
b10111110 @
b10111110 J
1!
#920
0!
#925
b11000010 -
b11000010 >
b11000000 @
b11000000 J
1!
#930
0!
#935
b11000100 -
b11000100 >
b11000010 @
b11000010 J
1!
#940
0!
#945
b11000110 -
b11000110 >
b11000100 @
b11000100 J
1!
#950
0!
#955
b11001000 -
b11001000 >
b11000110 @
b11000110 J
1!
#960
0!
#965
b11001010 -
b11001010 >
b11001000 @
b11001000 J
1!
#970
0!
#975
b11001100 -
b11001100 >
b11001010 @
b11001010 J
1!
#980
0!
#985
b11001110 -
b11001110 >
b11001100 @
b11001100 J
1!
#990
0!
#995
b11010000 -
b11010000 >
b11001110 @
b11001110 J
1!
#1000
0!
#1005
b11010010 -
b11010010 >
b11010000 @
b11010000 J
1!
